{
  "shiftDetails": [
    {
      "id": "411e",
      "date": "2024-09-05",
      "shift": "C",
      "mill": "URM",
      "lineNumber": "1",
      "railGrade": "880",
      "railSection": "60E1A1",
      "railLength": "65",
      "ieName": "IE Name 3",
      "rclIeName": "anjali"
    },
    {
      "id": "b69b",
      "formData": {
        "date": "16/09/2024",
        "shift": "C",
        "mill": "RSM",
        "ndt": "SR",
        "railGrade": "1080HH",
        "railSection": "136RE"
      }
    },
    {
      "id": "9b2a",
      "formData": {
        "date": "10/09/2024",
        "shift": "C",
        "mill": "RSM",
        "ndt": "SR",
        "railGrade": "350HT",
        "railSection": "136RE"
      }
    },
    {
      "id": "6c6b",
      "formData": {
        "date": "02/09/2024",
        "shift": "B",
        "mill": "URM",
        "lineNumber": "5",
        "railGrade": "350HT",
        "railSection": "UIC 60",
        "stdRailLength": "130",
        "otherIE": "",
        "rclIE": "ojas"
      }
    },
    {
      "id": "5c38",
      "formData": {
        "date": "21/09/2024",
        "shift": "C",
        "mill": "URM",
        "lineNumber": "5",
        "railGrade": "880",
        "railSection": "IRS 52",
        "stdRailLength": "130",
        "otherIE": "",
        "rclIE": "ojas"
      }
    },
    {
      "id": "ace5",
      "formData": {
        "date": "18/09/2024",
        "shift": "B",
        "mill": "RSM",
        "lineNumber": "2",
        "railGrade": "1080HH",
        "railSection": "UIC 60",
        "stdRailLength": "65",
        "otherIE": "",
        "rclIE": "ojas"
      }
    }
  ]
}